serpentTools/__init__.py
serpentTools/__main__.py
serpentTools/detectors.py
serpentTools/engines.py
serpentTools/messages.py
serpentTools/plot.py
serpentTools/seed.py
serpentTools/settings.py
serpentTools/variables.yaml
serpentTools/xs.py
serpentTools/data/InnerAssembly_res.m
serpentTools/data/__init__.py
serpentTools/data/bwr_0_dep.m
serpentTools/data/bwr_0_det0.m
serpentTools/data/bwr_1_dep.m
serpentTools/data/bwr_1_det0.m
serpentTools/data/bwr_badInventory_dep.m
serpentTools/data/bwr_det0.m
serpentTools/data/bwr_his0.m
serpentTools/data/bwr_longT_dep.m
serpentTools/data/bwr_missingT_dep.m
serpentTools/data/bwr_noxy_det0.m
serpentTools/data/bwr_sens0.m
serpentTools/data/bwr_smallxy_det0.m
serpentTools/data/demo.coe
serpentTools/data/demo_dep.m
serpentTools/data/demo_uncs.coe
serpentTools/data/depmtx_ref.m
serpentTools/data/flattop_sens.m
serpentTools/data/fuelPin_det0.m
serpentTools/data/hexplot_det0.m
serpentTools/data/plut_xs0.m
serpentTools/data/pwr_emptyAttributes_res.m
serpentTools/data/pwr_filter_res.m
serpentTools/data/pwr_noBU_res.m
serpentTools/data/pwr_noUniv_res.m
serpentTools/data/pwr_res.m
serpentTools/data/radplot_det0.m
serpentTools/data/ref_branch.coe
serpentTools/data/ref_dep.m
serpentTools/data/ref_det0.m
serpentTools/data/ref_mdx0.m
serpentTools/data/ref_noXS_mdx0.m
serpentTools/data/time_det0.m
serpentTools/io/__init__.py
serpentTools/io/base.py
serpentTools/io/hooks.py
serpentTools/objects/__init__.py
serpentTools/objects/base.py
serpentTools/objects/containers.py
serpentTools/objects/detectors.py
serpentTools/objects/materials.py
serpentTools/objects/xsdata.py
serpentTools/parsers/__init__.py
serpentTools/parsers/_collections.py
serpentTools/parsers/base.py
serpentTools/parsers/branching.py
serpentTools/parsers/bumat.py
serpentTools/parsers/depletion.py
serpentTools/parsers/depmatrix.py
serpentTools/parsers/detector.py
serpentTools/parsers/fissionMatrix.py
serpentTools/parsers/history.py
serpentTools/parsers/microxs.py
serpentTools-0.10.1.dist-info/LICENSE
serpentTools-0.10.1.dist-info/METADATA
serpentTools-0.10.1.dist-info/WHEEL
serpentTools-0.10.1.dist-info/top_level.txt
serpentTools-0.10.1.dist-info/RECORD
