Metadata-Version: 2.1
Name: serpentTools
Version: 0.10.1
Summary: A suite of parsers designed to make interacting with Serpent output files simple, scriptable, and flawless
Maintainer: Dan Kotlyar, Drew Johnson
License: MIT License
Project-URL: Homepage, https://github.com/CORE-GATECH-GROUP/serpent-tools
Project-URL: Bug Tracker, https://github.com/CORE-GATECH-GROUP/serpent-tools/issues
Classifier: Development Status :: 3 - Alpha
Classifier: Intended Audience :: Education
Classifier: Intended Audience :: Science/Research
Classifier: License :: OSI Approved :: MIT License
Classifier: Natural Language :: English
Classifier: Programming Language :: Python
Classifier: Programming Language :: Python :: 3.8
Classifier: Programming Language :: Python :: 3.9
Classifier: Programming Language :: Python :: 3.10
Classifier: Programming Language :: Python :: 3.11
Requires-Python: <3.12,>=3.8
License-File: LICENSE
Requires-Dist: numpy >=1.16.0
Requires-Dist: matplotlib !=3.3.4,>=2.2.3
Requires-Dist: pyyaml >=5.1.1
Provides-Extra: ci
Requires-Dist: jupyter ; extra == 'ci'
Provides-Extra: extras
Requires-Dist: pandas >1 ; extra == 'extras'
Requires-Dist: scipy ; extra == 'extras'
Provides-Extra: test
Requires-Dist: pytest >=6 ; extra == 'test'
Requires-Dist: pytest-cov ; extra == 'test'
Requires-Dist: coverage ; extra == 'test'
